Workbook

Sheet Cover
C4: FERRARI N.V.
C6: Credit Application: Integrated Financial Model
C7: Ferrari Residential Complex Miami | €1,100m annuity term loan
C11: Business Plan and Credit Assessment, 2022A-2030F | N11: EM032 Banking, IES FSV UK
C12: Matúš Balko | N12: November 2025
C13: Hypothetical case study: the Ferrari Residential Complex Miami project, its costs, financing and loan terms are made up for an academic exercise. Ferrari N.V. has not announced such a project. Historical 2022-2024 figures are Ferrari's reported data.
C14: Table of Contents | K14: Model Checks
C16: Inputs | K16: Does the balance sheet balance (standalone)? | N16: =IF(SUMPRODUCT(ABS(Model!D84:L84))<0.01,1,0) -> 1
C17: Income Statement | K17: Does the balance sheet balance (with project)? | N17: =IF(SUMPRODUCT(ABS(Model!D355:L355))<0.01,1,0) -> 1
C18: Revenue Build: Shipments and Revenue per Unit | K18: Is cash negative in any year? | N18: =IF(MIN(Model!D67:L67,Model!D345:L345)<0,1,0) -> 0
C19: Balance Sheet | K19: Annuity instalment matches Excel PMT? | N19: =IF(ABS(Model!F285)<0.000001,1,0) -> 1
C20: Cash Flow Statement | K20: Project loan fully repaid by Q4 2030? | N20: =IF(ABS(Model!J316)<0.01,1,0) -> 1
C21: Financial Analysis: Ferrari Standalone
C22: Working Capital Schedule
C23: Fixed Asset Schedule: PP&E and Intangible Assets
C24: Financing Schedule: Debt, Cash and Equity
C25: Residential Project: Ferrari Residential Complex Miami
C26: Project Loan: Annuity Repayment Schedule
C27: Pro-forma Statements: Ferrari with Project
C28: Credit Metrics: Standalone vs. with Project
C31: Key Figures | K31: Base-Case Credit Profile (2025F-2030F)
C33: Project loan amount (€m) | H33: =Model!F277 -> 1100 | K33: Peak net debt / EBITDA (standalone) | N33: =MAX(Model!G383:L383) -> 0.48709635
C34: Interest rate (fixed, p.a.) | H34: =Model!F278 -> 0.05 | K34: Peak net debt / EBITDA (with project) | N34: =MAX(Model!G390:L390) -> 0.71763682
C35: Quarterly annuity instalment (€m) | H35: =Model!F283 -> 145.34645 | K35: Minimum EBITDA / interest (with project) | N35: =MIN(Model!G391:L391) -> 16.102114
C36: Total interest over loan life (€m) | H36: =Model!F291 -> 154.0216 | K36: Minimum project DSCR (repayment years) | N36: =MIN(Model!G294:L294) -> 1.1808581
C37: Project IRR (unlevered, pre-tax) | H37: =Model!F262 -> 0.085332527 | K37: Lowest cash balance with project (€m) | N37: =MIN(Model!G345:L345) -> 1822.9143
C38: Break-even price incl. financing (€ per m²) | H38: =Model!F265 -> 17544.684
C41: Notes
C42: All figures in € millions unless stated. Historical data 2022-2024: Ferrari N.V. consolidated financial statements (Form 20-F), IFRS.
C43: Forecast drivers and project assumptions are on the Inputs sheet. Cash is derived from the cash flow statement, so the balance sheet balances without a plug.
C44: The project loan is a fixed-rate annuity: interest-only during construction, then eight equal quarterly instalments.
C45: Project interest is expensed through the income statement. This is a simplification, as under IAS 23 it would be capitalised into inventory and released on handover.
C46: Hypothetical case study: the Miami residential project and the loan are fictional and were made up for an academic exercise. Not affiliated with or endorsed by Ferrari N.V.

Sheet Inputs
B1: Ferrari N.V. | Credit Application Model
B3: Inputs: Forecast Drivers and Project Assumptions
B5: All figures in € millions unless stated | L5: Forecast
F6: Input | G6: 2025 | H6: 2026 | I6: 2027 | J6: 2028 | K6: 2029 | L6: 2030 | N6: Basis and source
B8: REVENUE: SHIPMENTS AND NET REVENUE PER UNIT
B9: EMEA shipment growth | C9: % y/y | G9: 0.01 | H9: 0.01 | I9: 0.01 | J9: 0.01 | K9: 0.01 | L9: 0.01 | N9: Volumes kept broadly stable (Ferrari CMD Oct-2025: growth driven by price and mix, not volume)
B10: Americas shipment growth | C10: % y/y | G10: 0.02 | H10: 0.02 | I10: 0.02 | J10: 0.02 | K10: 0.02 | L10: 0.02 | N10: Strongest region (2023-24 average +7.8% y/y), moderated
B11: Mainland China, Hong Kong and Taiwan shipment growth | C11: % y/y | G11: 0.02 | H11: 0.02 | I11: 0.02 | J11: 0.02 | K11: 0.02 | L11: 0.02 | N11: Gradual recovery from low 2024 base (-22.0% y/y)
B12: Rest of APAC shipment growth | C12: % y/y | G12: 0.01 | H12: 0.01 | I12: 0.01 | J12: 0.01 | K12: 0.01 | L12: 0.01 | N12: Volumes kept broadly stable
B13: Growth in net revenue per unit shipped | C13: % y/y | G13: 0.05 | H13: 0.035 | I13: 0.035 | J13: 0.035 | K13: 0.035 | L13: 0.035 | N13: Price, mix and personalisation. Gives about €7.1bn of revenue in 2025 (guidance of at least €7.1bn) and about €9.0bn in 2030 (Ferrari target, about 5% a year)
B15: OPERATING COSTS AND TAX
B16: Cost of sales | C16: % revenue | G16: 0.495 | H16: 0.493 | I16: 0.491 | J16: 0.489 | K16: 0.487 | L16: 0.485 | N16: Gradual improvement from 49.9% (2024A) toward Ferrari's 2030 target of an EBITDA margin of at least 40%
B17: Selling, general and administrative costs | C17: % revenue | G17: 0.084 | H17: 0.084 | I17: 0.084 | J17: 0.084 | K17: 0.084 | L17: 0.084 | N17: 2024A level (2022-24 range 7.7-8.4%)
B18: Research and development costs | C18: % revenue | G18: 0.132 | H18: 0.132 | I18: 0.132 | J18: 0.132 | K18: 0.132 | L18: 0.132 | N18: Close to 2024A (13.4%) as EV and new-model spending continues
B19: Other expenses, net | C19: % revenue | G19: 0.002 | H19: 0.002 | I19: 0.002 | J19: 0.002 | K19: 0.002 | L19: 0.002 | N19: 2024A level
B20: Result from investments | C20: €m | G20: 8 | H20: 8 | I20: 8 | J20: 8 | K20: 8 | L20: 8 | N20: Held at about the 2024A level (€8.2m)
B21: Effective tax rate | C21: % EBT | G21: 0.2 | H21: 0.2 | I21: 0.2 | J21: 0.2 | K21: 0.2 | L21: 0.2 | N21: 2022-24 average 20.3% (Italian patent box benefit)
B22: Non-controlling interests | C22: % net profit | G22: 0.003 | H22: 0.003 | I22: 0.003 | J22: 0.003 | K22: 0.003 | L22: 0.003 | N22: 2024A: 0.3%
B24: WORKING CAPITAL
B25: Trade receivables | C25: days | G25: 19 | H25: 19 | I25: 19 | J25: 19 | K25: 19 | L25: 19 | N25: 2024A: 19.1 days of revenue
B26: Inventories | C26: days | G26: 119 | H26: 119 | I26: 119 | J26: 119 | K26: 119 | L26: 119 | N26: 2024A: 119.3 days of cost of sales
B27: Trade payables | C27: days | G27: 104 | H27: 104 | I27: 104 | J27: 104 | K27: 104 | L27: 104 | N27: 2024A: 103.7 days of cost of sales
B28: Receivables from financing activities | C28: % revenue | G28: 0.249 | H28: 0.249 | I28: 0.249 | J28: 0.249 | K28: 0.249 | L28: 0.249 | N28: 2024A: 24.9%. Client and dealer financing grows with sales
B29: Other current assets | C29: % revenue | G29: 0.021 | H29: 0.021 | I29: 0.021 | J29: 0.021 | K29: 0.021 | L29: 0.021 | N29: 2024A: 2.1%
B30: Other liabilities | C30: % revenue | G30: 0.166 | H30: 0.166 | I30: 0.166 | J30: 0.166 | K30: 0.166 | L30: 0.166 | N30: 2024A: 16.6%, includes client advances and deferred income
B31: Provisions | C31: % revenue | G31: 0.031 | H31: 0.031 | I31: 0.031 | J31: 0.031 | K31: 0.031 | L31: 0.031 | N31: 2024A: 3.1%
B32: Days in period | C32: days | F32: 365
B33: Goodwill, investments, tax balances, deferred taxes, employee benefits and other financial liabilities are held at 2024A levels
B35: CAPITAL EXPENDITURE, DEPRECIATION AND AMORTISATION
B36: Capital expenditure on PP&E | C36: % revenue | G36: 0.058 | H36: 0.058 | I36: 0.058 | J36: 0.058 | K36: 0.058 | L36: 0.058 | N36: Total capex of 11.5% of revenue, about €4.7bn over 2026-30 (Ferrari target)
B37: Capital expenditure on intangible assets (capitalised development) | C37: % revenue | G37: 0.057 | H37: 0.057 | I37: 0.057 | J37: 0.057 | K37: 0.057 | L37: 0.057 | N37: See above (2024A: 7.2% PP&E + 7.6% intangibles during the e-building peak)
B38: Depreciation | C38: % opening PP&E | G38: 0.145 | H38: 0.145 | I38: 0.145 | J38: 0.145 | K38: 0.145 | L38: 0.145 | N38: Implied 2024A roll-forward: 14.5%
B39: Amortisation | C39: % opening intangibles | G39: 0.268 | H39: 0.268 | I39: 0.268 | J39: 0.268 | K39: 0.268 | L39: 0.268 | N39: Implied 2024A roll-forward: 26.8%
B41: FINANCING AND SHAREHOLDER RETURNS
B42: Change in existing debt | C42: €m | G42: 0 | H42: 0 | I42: 0 | J42: 0 | K42: 0 | L42: 0 | N42: Maturities refinanced, no new corporate debt in the base case
B43: Interest rate on existing debt | C43: % opening debt | G43: 0.044 | H43: 0.044 | I43: 0.044 | J43: 0.044 | K43: 0.044 | L43: 0.044 | N43: Keeps financial expenses at the 2024A level (€146m, about 4.4% of year-end 2024 debt)
B44: Interest income on cash | C44: % opening cash | G44: 0.02 | H44: 0.02 | I44: 0.02 | J44: 0.02 | K44: 0.02 | L44: 0.02 | N44: Euro deposit rates of about 2%. Excludes FX and hedging gains included in historical financial income
B45: Dividend payout | C45: % prior-yr profit | G45: 0.35 | H45: 0.35 | I45: 0.4 | J45: 0.4 | K45: 0.4 | L45: 0.4 | N45: 35% of prior-year profit, raised to 40% from 2027 (Ferrari Capital Markets Day, October 2025)
B46: Share repurchases | C46: €m | G46: 500 | H46: 700 | I46: 700 | J46: 700 | K46: 700 | L46: 700 | N46: Ferrari target of about €3.5bn of buybacks in 2026-30. 2025 in line with the 2022-24 average (€479m)
B48: RESIDENTIAL PROJECT: MIAMI
B49: Sellable residential area | C49: m² | F49: 90000 | N49: Credit application, section 4.1
B50: Planned units (260 apartments, 20 penthouses, 2 sky villas) | C50: units | F50: 282 | N50: Credit application, section 4.1
B51: Average selling price (base case) | C51: € per m² | F51: 20000 | N51: Low end of the €18,000-30,000 range. Ferrari brand premium of about 25% over Miami luxury comparables
B52: Tax rate on project profit | C52: % EBT | F52: 0.253 | N52: US federal 21% + Florida 5.5% (state tax deductible for federal purposes)
B53: Development cost (construction, design, amenities) | C53: €m | G53: 237.5 | H53: 437.5 | I53: 437.5 | J53: 312.5 | K53: 0 | L53: 0 | N53: Total €1,425m incl. land, construction, design, fees and sales costs. Heaviest in structural works (2026-27)
B54: Project loan drawdowns | C54: €m | G54: 0 | H54: 350 | I54: 437.5 | J54: 312.5 | K54: 0 | L54: 0 | N54: €1,100m term loan drawn in equal quarterly tranches after Ferrari's equity is spent
B55: Units handed over | C55: % of area | G55: 0 | H55: 0 | I55: 0 | J55: 0 | K55: 0.6 | L55: 0.4 | N55: Revenue recognised on handover (IFRS 15). Presales deposits not modelled
B56: Total development cost | C56: €m | F56: =SUM(G53:L53) -> 1425 | N56: Calculated
B57: Ferrari equity contribution | C57: €m | F57: =F56-F60 -> 325 | N57: Calculated: development cost less loan
B59: PROJECT LOAN: ANNUITY TERM LOAN
B60: Loan amount | C60: €m | F60: =SUM(G54:L54) -> 1100 | N60: Calculated: sum of drawdowns
B61: Interest rate (fixed) | C61: % p.a. | F61: 0.05 | N61: As proposed in the credit application. Corporate loan with full recourse to Ferrari N.V.
B62: Instalments per year | C62: # | F62: 4 | N62: Quarterly payments
B63: First repayment year | C63: year | F63: 2029 | N63: Interest-only during construction (2026-28)
B64: Repayment period | C64: years | F64: 2 | N64: Repaid from unit sales in 2029-30, must end by 2030 (model horizon)

Sheet Model
B1: Ferrari N.V. | Credit Application Model
B3: Income Statement
B4: All figures in € millions unless stated | F4: Actual | L4: Forecast
D5: 2022 | E5: =D5+1 -> 2023 | F5: =E5+1 -> 2024 | G5: =F5+1 -> 2025 | H5: =G5+1 -> 2026 | I5: =H5+1 -> 2027 | J5: =I5+1 -> 2028 | K5: =J5+1 -> 2029 | L5: =K5+1 -> 2030
B6: Net revenues | D6: 5095.254 | E6: 5970.146 | F6: 6676.668 | G6: =G48 -> 7106.9366 | H6: =H48 -> 7457.0329 | I6: =I48 -> 7824.5544 | J6: =J48 -> 8210.3775 | K6: =K48 -> 8615.4232 | L6: =L48 -> 9040.6594
B7: Cost of sales | D7: -2648.953 | E7: -2995.877 | F7: -3329.483 | G7: =-G6*Inputs!G16 -> -3517.9336 | H7: =-H6*Inputs!H16 -> -3676.3172 | I7: =-I6*Inputs!I16 -> -3841.8562 | J7: =-J6*Inputs!J16 -> -4014.8746 | K7: =-K6*Inputs!K16 -> -4195.7111 | L7: =-L6*Inputs!L16 -> -4384.7198
B8: Gross profit | D8: =SUM(D6:D7) -> 2446.301 | E8: =SUM(E6:E7) -> 2974.269 | F8: =SUM(F6:F7) -> 3347.185 | G8: =SUM(G6:G7) -> 3589.003 | H8: =SUM(H6:H7) -> 3780.7157 | I8: =SUM(I6:I7) -> 3982.6982 | J8: =SUM(J6:J7) -> 4195.5029 | K8: =SUM(K6:K7) -> 4419.7121 | L8: =SUM(L6:L7) -> 4655.9396
B9: Selling, general and administrative costs | D9: -427.974 | E9: -462.58 | F9: -561.144 | G9: =-G6*Inputs!G17 -> -596.98267 | H9: =-H6*Inputs!H17 -> -626.39076 | I9: =-I6*Inputs!I17 -> -657.26257 | J9: =-J6*Inputs!J17 -> -689.67171 | K9: =-K6*Inputs!K17 -> -723.69555 | L9: =-L6*Inputs!L17 -> -759.41539
B10: Research and development costs | D10: -775.572 | E10: -881.559 | F10: -894.092 | G10: =-G6*Inputs!G18 -> -938.11563 | H10: =-H6*Inputs!H18 -> -984.32834 | I10: =-I6*Inputs!I18 -> -1032.8412 | J10: =-J6*Inputs!J18 -> -1083.7698 | K10: =-K6*Inputs!K18 -> -1137.2359 | L10: =-L6*Inputs!L18 -> -1193.367
B11: Other expenses, net | D11: -21.548 | E11: -18.898 | F11: -12.443 | G11: =-G6*Inputs!G19 -> -14.213873 | H11: =-H6*Inputs!H19 -> -14.914066 | I11: =-I6*Inputs!I19 -> -15.649109 | J11: =-J6*Inputs!J19 -> -16.420755 | K11: =-K6*Inputs!K19 -> -17.230846 | L11: =-L6*Inputs!L19 -> -18.081319
B12: Result from investments | D12: 6.175 | E12: 6.137 | F12: 8.245 | G12: =Inputs!G20 -> 8 | H12: =Inputs!H20 -> 8 | I12: =Inputs!I20 -> 8 | J12: =Inputs!J20 -> 8 | K12: =Inputs!K20 -> 8 | L12: =Inputs!L20 -> 8
B13: Operating profit (EBIT) | D13: =SUM(D8,D9:D12) -> 1227.382 | E13: =SUM(E8,E9:E12) -> 1617.369 | F13: =SUM(F8,F9:F12) -> 1887.751 | G13: =SUM(G8,G9:G12) -> 2047.6908 | H13: =SUM(H8,H9:H12) -> 2163.0825 | I13: =SUM(I8,I9:I12) -> 2284.9453 | J13: =SUM(J8,J9:J12) -> 2413.6406 | K13: =SUM(K8,K9:K12) -> 2549.5498 | L13: =SUM(L8,L9:L12) -> 2693.0758
B14: Financial income | D14: 83.858 | E14: 132.319 | F14: 147.1 | G14: =G217 -> 34.84428 | H14: =H217 -> 41.208287 | I14: =I217 -> 45.023334 | J14: =J217 -> 48.122671 | K14: =K217 -> 52.171339 | L14: =L217 -> 57.291011
B15: Financial expenses | D15: -133.474 | E15: -147.334 | F15: -145.895 | G15: =-G213 -> -147.48307 | H15: =-H213 -> -147.48307 | I15: =-I213 -> -147.48307 | J15: =-J213 -> -147.48307 | K15: =-K213 -> -147.48307 | L15: =-L213 -> -147.48307
B16: Profit before taxes | D16: =SUM(D13,D14:D15) -> 1177.766 | E16: =SUM(E13,E14:E15) -> 1602.354 | F16: =SUM(F13,F14:F15) -> 1888.956 | G16: =SUM(G13,G14:G15) -> 1935.052 | H16: =SUM(H13,H14:H15) -> 2056.8077 | I16: =SUM(I13,I14:I15) -> 2182.4856 | J16: =SUM(J13,J14:J15) -> 2314.2802 | K16: =SUM(K13,K14:K15) -> 2454.2381 | L16: =SUM(L13,L14:L15) -> 2602.8838
B17: Income tax expense | D17: -238.472 | E17: -344.897 | F17: -363.043 | G17: =-G16*Inputs!G21 -> -387.0104 | H17: =-H16*Inputs!H21 -> -411.36154 | I17: =-I16*Inputs!I21 -> -436.49712 | J17: =-J16*Inputs!J21 -> -462.85604 | K17: =-K16*Inputs!K21 -> -490.84762 | L17: =-L16*Inputs!L21 -> -520.57676
B18: Net profit | D18: =SUM(D16:D17) -> 939.294 | E18: =SUM(E16:E17) -> 1257.457 | F18: =SUM(F16:F17) -> 1525.913 | G18: =SUM(G16:G17) -> 1548.0416 | H18: =SUM(H16:H17) -> 1645.4462 | I18: =SUM(I16:I17) -> 1745.9885 | J18: =SUM(J16:J17) -> 1851.4242 | K18: =SUM(K16:K17) -> 1963.3905 | L18: =SUM(L16:L17) -> 2082.307
B19: Attributable to non-controlling interests | D19: 6.68 | E19: 5.409 | F19: 4.036 | G19: =G18*Inputs!G22 -> 4.6441248 | H19: =H18*Inputs!H22 -> 4.9363385 | I19: =I18*Inputs!I22 -> 5.2379654 | J19: =J18*Inputs!J22 -> 5.5542725 | K19: =K18*Inputs!K22 -> 5.8901715 | L19: =L18*Inputs!L22 -> 6.2469211
B20: Attributable to owners of the parent | D20: =D18-D19 -> 932.614 | E20: =E18-E19 -> 1252.048 | F20: =F18-F19 -> 1521.877 | G20: =G18-G19 -> 1543.3975 | H20: =H18-H19 -> 1640.5098 | I20: =I18-I19 -> 1740.7505 | J20: =J18-J19 -> 1845.8699 | K20: =K18-K19 -> 1957.5003 | L20: =L18-L19 -> 2076.0601
B21: Memo:
B22: Depreciation and amortisation | D22: 546.225 | E22: 662.305 | F22: 666.777 | G22: =G198 -> 679.41163 | H22: =H198 -> 698.28058 | I22: =I198 -> 723.00728 | J22: =J198 -> 752.41652 | K22: =K198 -> 785.68944 | L22: =L198 -> 822.26701
B23: EBITDA | D23: =D13+D22 -> 1773.607 | E23: =E13+E22 -> 2279.674 | F23: =F13+F22 -> 2554.528 | G23: =G13+G22 -> 2727.1024 | H23: =H13+H22 -> 2861.3631 | I23: =I13+I22 -> 3007.9526 | J23: =J13+J22 -> 3166.0571 | K23: =K13+K22 -> 3335.2393 | L23: =L13+L22 -> 3515.3429
B24: Assumptions:
B25: Revenue growth | E25: =E6/D6-1 -> 0.17170724 | F25: =F6/E6-1 -> 0.1183425 | G25: =G6/F6-1 -> 0.064443608 | H25: =H6/G6-1 -> 0.049261214 | I25: =I6/H6-1 -> 0.049285216 | J25: =J6/I6-1 -> 0.049309273 | K25: =K6/J6-1 -> 0.049333387 | L25: =L6/K6-1 -> 0.049357555
B26: Gross margin | D26: =D8/D6 -> 0.48011365 | E26: =E8/E6 -> 0.49819033 | F26: =F8/F6 -> 0.50132566 | G26: =G8/G6 -> 0.505 | H26: =H8/H6 -> 0.507 | I26: =I8/I6 -> 0.509 | J26: =J8/J6 -> 0.511 | K26: =K8/K6 -> 0.513 | L26: =L8/L6 -> 0.515
B27: Cost of sales (% of revenue) | D27: =-D7/D6 -> 0.51988635 | E27: =-E7/E6 -> 0.50180967 | F27: =-F7/F6 -> 0.49867434 | G27: =Inputs!G16 -> 0.495 | H27: =Inputs!H16 -> 0.493 | I27: =Inputs!I16 -> 0.491 | J27: =Inputs!J16 -> 0.489 | K27: =Inputs!K16 -> 0.487 | L27: =Inputs!L16 -> 0.485
B28: SG&A (% of revenue) | D28: =-D9/D6 -> 0.083994635 | E28: =-E9/E6 -> 0.077482192 | F28: =-F9/F6 -> 0.084045515 | G28: =Inputs!G17 -> 0.084 | H28: =Inputs!H17 -> 0.084 | I28: =Inputs!I17 -> 0.084 | J28: =Inputs!J17 -> 0.084 | K28: =Inputs!K17 -> 0.084 | L28: =Inputs!L17 -> 0.084
B29: R&D (% of revenue) | D29: =-D10/D6 -> 0.15221459 | E29: =-E10/E6 -> 0.14766121 | F29: =-F10/F6 -> 0.1339129 | G29: =Inputs!G18 -> 0.132 | H29: =Inputs!H18 -> 0.132 | I29: =Inputs!I18 -> 0.132 | J29: =Inputs!J18 -> 0.132 | K29: =Inputs!K18 -> 0.132 | L29: =Inputs!L18 -> 0.132
B30: Other expenses, net (% of revenue) | D30: =-D11/D6 -> 0.0042290335 | E30: =-E11/E6 -> 0.0031654167 | F30: =-F11/F6 -> 0.0018636541 | G30: =Inputs!G19 -> 0.002 | H30: =Inputs!H19 -> 0.002 | I30: =Inputs!I19 -> 0.002 | J30: =Inputs!J19 -> 0.002 | K30: =Inputs!K19 -> 0.002 | L30: =Inputs!L19 -> 0.002
B31: EBITDA margin | D31: =D23/D6 -> 0.34809001 | E31: =E23/E6 -> 0.3818456 | F31: =F23/F6 -> 0.38260522 | G31: =G23/G6 -> 0.38372404 | H31: =H23/H6 -> 0.38371335 | I31: =I23/I6 -> 0.38442478 | J31: =J23/J6 -> 0.38561651 | K31: =K23/K6 -> 0.38712425 | L31: =L23/L6 -> 0.388837
B32: EBIT margin | D32: =D13/D6 -> 0.2408873 | E32: =E13/E6 -> 0.27090946 | F32: =F13/F6 -> 0.28273849 | G32: =G13/G6 -> 0.28812566 | H32: =H13/H6 -> 0.29007281 | I32: =I13/I6 -> 0.29202242 | J32: =J13/J6 -> 0.29397438 | K32: =K13/K6 -> 0.29592857 | L32: =L13/L6 -> 0.29788489
B33: Effective tax rate | D33: =-D17/D16 -> 0.20247825 | E33: =-E17/E16 -> 0.21524395 | F33: =-F17/F16 -> 0.19219241 | G33: =Inputs!G21 -> 0.2 | H33: =Inputs!H21 -> 0.2 | I33: =Inputs!I21 -> 0.2 | J33: =Inputs!J21 -> 0.2 | K33: =Inputs!K21 -> 0.2 | L33: =Inputs!L21 -> 0.2
B34: Non-controlling interests (% of net profit) | D34: =D19/D18 -> 0.0071117243 | E34: =E19/E18 -> 0.0043015387 | F34: =F19/F18 -> 0.0026449739 | G34: =Inputs!G22 -> 0.003 | H34: =Inputs!H22 -> 0.003 | I34: =Inputs!I22 -> 0.003 | J34: =Inputs!J22 -> 0.003 | K34: =Inputs!K22 -> 0.003 | L34: =Inputs!L22 -> 0.003
B36: Revenue Build: Shipments and Revenue per Unit
B37: Shipments in units, revenue in € millions | F37: Actual | L37: Forecast
D38: =D$5 -> 2022 | E38: =E$5 -> 2023 | F38: =F$5 -> 2024 | G38: =G$5 -> 2025 | H38: =H$5 -> 2026 | I38: =I$5 -> 2027 | J38: =J$5 -> 2028 | K38: =K$5 -> 2029 | L38: =L$5 -> 2030
B39: SHIPMENTS BY REGION
B40: EMEA | D40: 5958 | E40: 6063 | F40: 6204 | G40: =F40*(1+Inputs!G9) -> 6266.04 | H40: =G40*(1+Inputs!H9) -> 6328.7004 | I40: =H40*(1+Inputs!I9) -> 6391.9874 | J40: =I40*(1+Inputs!J9) -> 6455.9073 | K40: =J40*(1+Inputs!K9) -> 6520.4664 | L40: =K40*(1+Inputs!L9) -> 6585.671
B41: Americas | D41: 3447 | E41: 3811 | F41: 4003 | G41: =F41*(1+Inputs!G10) -> 4083.06 | H41: =G41*(1+Inputs!H10) -> 4164.7212 | I41: =H41*(1+Inputs!I10) -> 4248.0156 | J41: =I41*(1+Inputs!J10) -> 4332.9759 | K41: =J41*(1+Inputs!K10) -> 4419.6355 | L41: =K41*(1+Inputs!L10) -> 4508.0282
B42: Mainland China, Hong Kong and Taiwan | D42: 1552 | E42: 1490 | F42: 1162 | G42: =F42*(1+Inputs!G11) -> 1185.24 | H42: =G42*(1+Inputs!H11) -> 1208.9448 | I42: =H42*(1+Inputs!I11) -> 1233.1237 | J42: =I42*(1+Inputs!J11) -> 1257.7862 | K42: =J42*(1+Inputs!K11) -> 1282.9419 | L42: =K42*(1+Inputs!L11) -> 1308.6007
B43: Rest of APAC | D43: 2264 | E43: 2299 | F43: 2383 | G43: =F43*(1+Inputs!G12) -> 2406.83 | H43: =G43*(1+Inputs!H12) -> 2430.8983 | I43: =H43*(1+Inputs!I12) -> 2455.2073 | J43: =I43*(1+Inputs!J12) -> 2479.7594 | K43: =J43*(1+Inputs!K12) -> 2504.5569 | L43: =K43*(1+Inputs!L12) -> 2529.6025
B44: Total shipments | D44: =SUM(D40:D43) -> 13221 | E44: =SUM(E40:E43) -> 13663 | F44: =SUM(F40:F43) -> 13752 | G44: =SUM(G40:G43) -> 13941.17 | H44: =SUM(H40:H43) -> 14133.265 | I44: =SUM(I40:I43) -> 14328.334 | J44: =SUM(J40:J43) -> 14526.429 | K44: =SUM(K40:K43) -> 14727.601 | L44: =SUM(L40:L43) -> 14931.902
B45: Shipment growth | E45: =E44/D44-1 -> 0.033431662 | F45: =F44/E44-1 -> 0.0065139428 | G45: =G44/F44-1 -> 0.013755817 | H45: =H44/G44-1 -> 0.013778951 | I45: =I44/H44-1 -> 0.013802141 | J45: =J44/I44-1 -> 0.013825385 | K45: =K44/J44-1 -> 0.013848683 | L45: =L44/K44-1 -> 0.013872034
B46: Net revenue per unit shipped (€ thousands) | D46: =D6*1000/D44 -> 385.39097 | E46: =E6*1000/E44 -> 436.95718 | F46: =F6*1000/F44 -> 485.50524 | G46: =F46*(1+Inputs!G13) -> 509.7805 | H46: =G46*(1+Inputs!H13) -> 527.62281 | I46: =H46*(1+Inputs!I13) -> 546.08961 | J46: =I46*(1+Inputs!J13) -> 565.20275 | K46: =J46*(1+Inputs!K13) -> 584.98485 | L46: =K46*(1+Inputs!L13) -> 605.45932
B47: Growth in net revenue per unit | E47: =E46/D46-1 -> 0.13380234 | F47: =F46/E46-1 -> 0.11110483 | G47: =Inputs!G13 -> 0.05 | H47: =Inputs!H13 -> 0.035 | I47: =Inputs!I13 -> 0.035 | J47: =Inputs!J13 -> 0.035 | K47: =Inputs!K13 -> 0.035 | L47: =Inputs!L13 -> 0.035
B48: Net revenues | D48: =D44*D46/1000 -> 5095.254 | E48: =E44*E46/1000 -> 5970.146 | F48: =F44*F46/1000 -> 6676.668 | G48: =G44*G46/1000 -> 7106.9366 | H48: =H44*H46/1000 -> 7457.0329 | I48: =I44*I46/1000 -> 7824.5544 | J48: =J44*J46/1000 -> 8210.3775 | K48: =K44*K46/1000 -> 8615.4232 | L48: =L44*L46/1000 -> 9040.6594
B49: Revenue growth | E49: =E48/D48-1 -> 0.17170724 | F49: =F48/E48-1 -> 0.1183425 | G49: =G48/F48-1 -> 0.064443608 | H49: =H48/G48-1 -> 0.049261214 | I49: =I48/H48-1 -> 0.049285216 | J49: =J48/I48-1 -> 0.049309273 | K49: =K48/J48-1 -> 0.049333387 | L49: =L48/K48-1 -> 0.049357555
B51: Balance Sheet
B52: All figures in € millions unless stated | F52: Actual | L52: Forecast
D53: =D$5 -> 2022 | E53: =E$5 -> 2023 | F53: =F$5 -> 2024 | G53: =G$5 -> 2025 | H53: =H$5 -> 2026 | I53: =I$5 -> 2027 | J53: =J$5 -> 2028 | K53: =K$5 -> 2029 | L53: =L$5 -> 2030
B54: ASSETS
B55: Goodwill | D55: 785.182 | E55: 785.182 | F55: 785.182 | G55: =F55 -> 785.182 | H55: =G55 -> 785.182 | I55: =H55 -> 785.182 | J55: =I55 -> 785.182 | K55: =J55 -> 785.182 | L55: =K55 -> 785.182
B56: Intangible assets | D56: 1307.388 | E56: 1419.699 | F56: 1545.664 | G56: =G197 -> 1536.5214 | H56: =H197 -> 1549.7846 | I56: =I197 -> 1580.4419 | J56: =J197 -> 1624.875 | K56: =K197 -> 1680.4876 | L56: =L197 -> 1745.4345
B57: Property, plant and equipment | D57: 1457.825 | E57: 1575.2 | F57: 1828.784 | G57: =G192 -> 1975.8126 | H57: =H192 -> 2121.8277 | I57: =I192 -> 2267.9869 | J57: =J192 -> 2415.3307 | K57: =K192 -> 2564.8023 | L57: =L192 -> 2717.2642
B58: Investments and other financial assets | D58: 59.534 | E58: 67.671 | F58: 80.822 | G58: =F58 -> 80.822 | H58: =G58 -> 80.822 | I58: =H58 -> 80.822 | J58: =I58 -> 80.822 | K58: =J58 -> 80.822 | L58: =K58 -> 80.822
B59: Deferred tax assets | D59: 203.382 | E59: 217.553 | F59: 236.791 | G59: =F59 -> 236.791 | H59: =G59 -> 236.791 | I59: =H59 -> 236.791 | J59: =I59 -> 236.791 | K59: =J59 -> 236.791 | L59: =K59 -> 236.791
B60: Total non-current assets | D60: =SUM(D55:D59) -> 3813.311 | E60: =SUM(E55:E59) -> 4065.305 | F60: =SUM(F55:F59) -> 4477.243 | G60: =SUM(G55:G59) -> 4615.1291 | H60: =SUM(H55:H59) -> 4774.4073 | I60: =SUM(I55:I59) -> 4951.2238 | J60: =SUM(J55:J59) -> 5143.0006 | K60: =SUM(K55:K59) -> 5348.0849 | L60: =SUM(L55:L59) -> 5565.4937
B61: Inventories | D61: 674.662 | E61: 948.514 | F61: 1088.194 | G61: =G178 -> 1146.9427 | H61: =H178 -> 1198.5801 | I61: =I178 -> 1252.5504 | J61: =J178 -> 1308.9591 | K61: =K178 -> 1367.9168 | L61: =L178 -> 1429.5388
B62: Trade receivables | D62: 232.414 | E62: 261.38 | F62: 349.176 | G62: =G177 -> 369.95012 | H62: =H177 -> 388.17432 | I62: =I177 -> 407.30557 | J62: =J177 -> 427.38951 | K62: =K177 -> 448.47408 | L62: =L177 -> 470.60967
B63: Receivables from financing activities | D63: 1399.997 | E63: 1451.158 | F63: 1661.632 | G63: =G180 -> 1769.6272 | H63: =H180 -> 1856.8012 | I63: =I180 -> 1948.314 | J63: =J180 -> 2044.384 | K63: =K180 -> 2145.2404 | L63: =L180 -> 2251.1242
B64: Tax receivables | D64: 16.054 | E64: 11.616 | F64: 15.918 | G64: =F64 -> 15.918 | H64: =G64 -> 15.918 | I64: =H64 -> 15.918 | J64: =I64 -> 15.918 | K64: =J64 -> 15.918 | L64: =K64 -> 15.918
B65: Other current assets | D65: 153.183 | E65: 130.228 | F65: 137.763 | G65: =G181 -> 149.24567 | H65: =H181 -> 156.59769 | I65: =I181 -> 164.31564 | J65: =J181 -> 172.41793 | K65: =K181 -> 180.92389 | L65: =L181 -> 189.85385
B66: Current financial assets | D66: 87.301 | E66: 61.13 | F66: 25.006 | G66: =F66 -> 25.006 | H66: =G66 -> 25.006 | I66: =H66 -> 25.006 | J66: =I66 -> 25.006 | K66: =J66 -> 25.006 | L66: =K66 -> 25.006
B67: Cash and cash equivalents | D67: 1388.901 | E67: 1121.981 | F67: 1742.214 | G67: =G114 -> 2060.4143 | H67: =H114 -> 2251.1667 | I67: =I114 -> 2406.1335 | J67: =J114 -> 2608.567 | K67: =K114 -> 2864.5505 | L67: =L114 -> 3179.2564
B68: Total current assets | D68: =SUM(D61:D67) -> 3952.512 | E68: =SUM(E61:E67) -> 3986.007 | F68: =SUM(F61:F67) -> 5019.903 | G68: =SUM(G61:G67) -> 5537.1041 | H68: =SUM(H61:H67) -> 5892.2441 | I68: =SUM(I61:I67) -> 6219.5432 | J68: =SUM(J61:J67) -> 6602.6415 | K68: =SUM(K61:K67) -> 7048.0297 | L68: =SUM(L61:L67) -> 7561.3069
B69: Total assets | D69: =D60+D68 -> 7765.823 | E69: =E60+E68 -> 8051.312 | F69: =F60+F68 -> 9497.146 | G69: =G60+G68 -> 10152.233 | H69: =H60+H68 -> 10666.651 | I69: =I60+I68 -> 11170.767 | J69: =J60+J68 -> 11745.642 | K69: =K60+K68 -> 12396.115 | L69: =L60+L68 -> 13126.801
B70: EQUITY AND LIABILITIES
B71: Equity attributable to owners of the parent | D71: 2592.857 | E71: 3060.888 | F71: 3533.946 | G71: =G224 -> 4044.6865 | H71: =H224 -> 4445.0073 | I71: =I224 -> 4829.5538 | J71: =J224 -> 5279.1235 | K71: =K224 -> 5798.2759 | L71: =L224 -> 6391.3358
B72: Non-controlling interests | D72: 9.63 | E72: 9.734 | F72: 9.292 | G72: =F72 -> 9.292 | H72: =G72 -> 9.292 | I72: =H72 -> 9.292 | J72: =I72 -> 9.292 | K72: =J72 -> 9.292 | L72: =K72 -> 9.292
B73: Total equity | D73: =SUM(D71:D72) -> 2602.487 | E73: =SUM(E71:E72) -> 3070.622 | F73: =SUM(F71:F72) -> 3543.238 | G73: =SUM(G71:G72) -> 4053.9785 | H73: =SUM(H71:H72) -> 4454.2993 | I73: =SUM(I71:I72) -> 4838.8458 | J73: =SUM(J71:J72) -> 5288.4155 | K73: =SUM(K71:K72) -> 5807.5679 | L73: =SUM(L71:L72) -> 6400.6278
B74: Employee benefits | D74: 110.807 | E74: 123.045 | F74: 134.147 | G74: =F74 -> 134.147 | H74: =G74 -> 134.147 | I74: =H74 -> 134.147 | J74: =I74 -> 134.147 | K74: =J74 -> 134.147 | L74: =K74 -> 134.147
B75: Provisions | D75: 180.694 | E75: 187.276 | F75: 206.212 | G75: =G183 -> 220.31503 | H75: =H183 -> 231.16802 | I75: =I183 -> 242.56119 | J75: =J183 -> 254.5217 | K75: =K183 -> 267.07812 | L75: =L183 -> 280.26044
B76: Deferred tax liabilities | D76: 126.507 | E76: 136.846 | F76: 110.016 | G76: =F76 -> 110.016 | H76: =G76 -> 110.016 | I76: =H76 -> 110.016 | J76: =I76 -> 110.016 | K76: =J76 -> 110.016 | L76: =K76 -> 110.016
B77: Debt | D77: 2811.779 | E77: 2477.186 | F77: 3351.888 | G77: =G211 -> 3351.888 | H77: =H211 -> 3351.888 | I77: =I211 -> 3351.888 | J77: =J211 -> 3351.888 | K77: =K211 -> 3351.888 | L77: =L211 -> 3351.888
B78: Other liabilities | D78: 952.025 | E78: 1022.967 | F78: 1106.221 | G78: =G182 -> 1179.7515 | H78: =H182 -> 1237.8675 | I78: =I182 -> 1298.876 | J78: =J182 -> 1362.9227 | K78: =K182 -> 1430.1603 | L78: =L182 -> 1500.7495
B79: Other financial liabilities | D79: 19.993 | E79: 13.539 | F79: 61.894 | G79: =F79 -> 61.894 | H79: =G79 -> 61.894 | I79: =H79 -> 61.894 | J79: =I79 -> 61.894 | K79: =J79 -> 61.894 | L79: =K79 -> 61.894
B80: Trade payables | D80: 902.968 | E80: 930.56 | F80: 945.657 | G80: =G179 -> 1002.3701 | H80: =H179 -> 1047.4986 | I80: =I179 -> 1094.6659 | J80: =J179 -> 1143.9643 | K80: =K179 -> 1195.4903 | L80: =L179 -> 1249.3448
B81: Tax payables | D81: 58.563 | E81: 89.271 | F81: 37.873 | G81: =F81 -> 37.873 | H81: =G81 -> 37.873 | I81: =H81 -> 37.873 | J81: =I81 -> 37.873 | K81: =J81 -> 37.873 | L81: =K81 -> 37.873
B82: Total liabilities | D82: =SUM(D74:D81) -> 5163.336 | E82: =SUM(E74:E81) -> 4980.69 | F82: =SUM(F74:F81) -> 5953.908 | G82: =SUM(G74:G81) -> 6098.2546 | H82: =SUM(H74:H81) -> 6212.3521 | I82: =SUM(I74:I81) -> 6331.9211 | J82: =SUM(J74:J81) -> 6457.2266 | K82: =SUM(K74:K81) -> 6588.5467 | L82: =SUM(L74:L81) -> 6726.1727
B83: Total equity and liabilities | D83: =D73+D82 -> 7765.823 | E83: =E73+E82 -> 8051.312 | F83: =F73+F82 -> 9497.146 | G83: =G73+G82 -> 10152.233 | H83: =H73+H82 -> 10666.651 | I83: =I73+I82 -> 11170.767 | J83: =J73+J82 -> 11745.642 | K83: =K73+K82 -> 12396.115 | L83: =L73+L82 -> 13126.801
B84: Balance check | D84: =ROUND(D69-D83,3) -> 0 | E84: =ROUND(E69-E83,3) -> 0 | F84: =ROUND(F69-F83,3) -> 0 | G84: =ROUND(G69-G83,3) -> 0 | H84: =ROUND(H69-H83,3) -> 0 | I84: =ROUND(I69-I83,3) -> 0 | J84: =ROUND(J69-J83,3) -> 0 | K84: =ROUND(K69-K83,3) -> 0 | L84: =ROUND(L69-L83,3) -> 0
B85: Is cash negative? | D85: =IF(D67<0,1,0) -> 0 | E85: =IF(E67<0,1,0) -> 0 | F85: =IF(F67<0,1,0) -> 0 | G85: =IF(G67<0,1,0) -> 0 | H85: =IF(H67<0,1,0) -> 0 | I85: =IF(I67<0,1,0) -> 0 | J85: =IF(J67<0,1,0) -> 0 | K85: =IF(K67<0,1,0) -> 0 | L85: =IF(L67<0,1,0) -> 0
B87: Cash Flow Statement
B88: All figures in € millions unless stated | F88: Actual | L88: Forecast
D89: =D$5 -> 2022 | E89: =E$5 -> 2023 | F89: =F$5 -> 2024 | G89: =G$5 -> 2025 | H89: =H$5 -> 2026 | I89: =I$5 -> 2027 | J89: =J$5 -> 2028 | K89: =K$5 -> 2029 | L89: =L$5 -> 2030
B90: CASH FROM OPERATING ACTIVITIES
B91: Net profit | D91: =D18 -> 939.294 | E91: =E18 -> 1257.457 | F91: =F18 -> 1525.913 | G91: =G18 -> 1548.0416 | H91: =H18 -> 1645.4462 | I91: =I18 -> 1745.9885 | J91: =J18 -> 1851.4242 | K91: =K18 -> 1963.3905 | L91: =L18 -> 2082.307
B92: Depreciation and amortisation | D92: =D22 -> 546.225 | E92: =E22 -> 662.305 | F92: =F22 -> 666.777 | G92: =G22 -> 679.41163 | H92: =H22 -> 698.28058 | I92: =I22 -> 723.00728 | J92: =J22 -> 752.41652 | K92: =K22 -> 785.68944 | L92: =L22 -> 822.26701
B93: Change in trade receivables | D93: -48.4 | E93: -33.381 | F93: -94.029 | G93: =F62-G62 -> -20.774123 | H93: =G62-H62 -> -18.224192 | I93: =H62-I62 -> -19.131255 | J93: =I62-J62 -> -20.083942 | K93: =J62-K62 -> -21.084572 | L93: =K62-L62 -> -22.135584
B94: Change in inventories | D94: -153.89 | E94: -309.564 | F94: -157.526 | G94: =F61-G61 -> -58.748737 | H94: =G61-H61 -> -51.637398 | I94: =H61-I61 -> -53.970242 | J94: =I61-J61 -> -56.408733 | K94: =J61-K61 -> -58.957658 | L94: =K61-L61 -> -61.622022
B95: Change in receivables from financing activities | D95: -187.89 | E95: -107.247 | F95: -118.687 | G95: =F63-G63 -> -107.99521 | H95: =G63-H63 -> -87.173985 | I95: =H63-I63 -> -91.512847 | J95: =I63-J63 -> -96.06995 | K95: =J63-K63 -> -100.85639 | L95: =K63-L63 -> -105.88382
B96: Change in trade payables | D96: 103.981 | E96: 43.277 | F96: 7.672 | G96: =G80-F80 -> 56.713123 | H96: =H80-G80 -> 45.128482 | I96: =I80-H80 -> 47.16727 | J96: =J80-I80 -> 49.298389 | K96: =K80-J80 -> 51.526021 | L96: =L80-K80 -> 53.854541
B97: Change in other operating assets and liabilities | D97: 140.008 | E97: 48.642 | F97: -20.045 | G97: =(F65-G65)+(G78-F78) -> 62.047804 | H97: =(G65-H65)+(H78-G78) -> 50.763967 | I97: =(H65-I65)+(I78-H78) -> 53.290614 | J97: =(I65-J65)+(J78-I78) -> 55.944348 | K97: =(J65-K65)+(K78-J78) -> 58.731631 | L97: =(K65-L65)+(L78-K78) -> 61.659253
B98: Other operating items, net | D98: 64.012 | E98: 155.148 | F98: 116.581 | G98: =(G75-F75)+(G74-F74)+(G81-F81)+(F64-G64)+(F59-G59)+(G76-F76) -> 14.103034 | H98: =(H75-G75)+(H74-G74)+(H81-G81)+(G64-H64)+(G59-H59)+(H76-G76) -> 10.852986 | I98: =(I75-H75)+(I74-H74)+(I81-H81)+(H64-I64)+(H59-I59)+(I76-H76) -> 11.393166 | J98: =(J75-I75)+(J74-I74)+(J81-I81)+(I64-J64)+(I59-J59)+(J76-I76) -> 11.960516 | K98: =(K75-J75)+(K74-J74)+(K81-J81)+(J64-K64)+(J59-K59)+(K76-J76) -> 12.556418 | L98: =(L75-K75)+(L74-K74)+(L81-K81)+(K64-L64)+(K59-L59)+(L76-K76) -> 13.182323
B99: Cash flows from operating activities | D99: =SUM(D91:D98) -> 1403.34 | E99: =SUM(E91:E98) -> 1716.637 | F99: =SUM(F91:F98) -> 1926.656 | G99: =SUM(G91:G98) -> 2172.7991 | H99: =SUM(H91:H98) -> 2293.4366 | I99: =SUM(I91:I98) -> 2416.2325 | J99: =SUM(J91:J98) -> 2548.4813 | K99: =SUM(K91:K98) -> 2690.9954 | L99: =SUM(L91:L98) -> 2843.6287
B100: CASH FROM INVESTING ACTIVITIES
B101: Investments in intangible assets | D101: -456.894 | E101: -487.148 | F101: -506.874 | G101: =-G195 -> -405.09538 | H101: =-H195 -> -425.05088 | I101: =-I195 -> -445.9996 | J101: =-J195 -> -467.99152 | K101: =-K195 -> -491.07912 | L101: =-L195 -> -515.31759
B102: Investments in property, plant and equipment | D102: -347.725 | E102: -381.762 | F102: -482.277 | G102: =-G190 -> -412.20232 | H102: =-H190 -> -432.50791 | I102: =-I190 -> -453.82415 | J102: =-J190 -> -476.20189 | K102: =-K190 -> -499.69455 | L102: =-L190 -> -524.35825
B103: Other investing activities, net | D103: -0.789 | E103: 2.458 | F103: 2.041 | G103: =(F55-G55)+(F58-G58)+(F66-G66) -> 0 | H103: =(G55-H55)+(G58-H58)+(G66-H66) -> 0 | I103: =(H55-I55)+(H58-I58)+(H66-I66) -> 0 | J103: =(I55-J55)+(I58-J58)+(I66-J66) -> 0 | K103: =(J55-K55)+(J58-K58)+(J66-K66) -> 0 | L103: =(K55-L55)+(K58-L58)+(K66-L66) -> 0
B104: Cash flows used in investing activities | D104: =SUM(D101:D103) -> -805.408 | E104: =SUM(E101:E103) -> -866.452 | F104: =SUM(F101:F103) -> -987.11 | G104: =SUM(G101:G103) -> -817.29771 | H104: =SUM(H101:H103) -> -857.55878 | I104: =SUM(I101:I103) -> -899.82375 | J104: =SUM(J101:J103) -> -944.19341 | K104: =SUM(K101:K103) -> -990.77367 | L104: =SUM(L101:L103) -> -1039.6758
...
